README.txt
setup.py
zencheck.py
ZenCheck.egg-info/PKG-INFO
ZenCheck.egg-info/SOURCES.txt
ZenCheck.egg-info/dependency_links.txt
ZenCheck.egg-info/entry_points.txt
ZenCheck.egg-info/requires.txt
ZenCheck.egg-info/top_level.txt
ZenCheck.egg-info/zip-safe