Metadata-Version: 1.1
Name: ZenCheck
Version: 1.1
Summary: A wrapper for various code/markup syntax checking tools.
Home-page: https://bitbucket.org/rockyburt/zenchecker/
Author: Rocky Burt
Author-email: rocky@serverzen.com
License: BSD
Platform: UNKNOWN
Classifier: Programming Language :: Python
Classifier: Topic :: Software Development :: Libraries :: Python Modules
